catch22_C.cp310-win_amd64.pyd
pycatch22/__init__.py
pycatch22/catch22.py
pycatch22-0.4.5.dist-info/LICENSE
pycatch22-0.4.5.dist-info/METADATA
pycatch22-0.4.5.dist-info/WHEEL
pycatch22-0.4.5.dist-info/top_level.txt
pycatch22-0.4.5.dist-info/RECORD
