Metadata-Version: 2.1
Name: pycatch22
Version: 0.4.5
Summary: 22 CAnonical Time-series Features
Author: Carl H Lubba
Author-email: carl.lubba@gmx.de
Maintainer: Ben D Fulcher
Maintainer-email: ben.fulcher@sydney.edu.au
License: GNU General Public License v3 (GPLv3)
Project-URL: GitHub Repository (pycatch22), https://github.com/DynamicsAndNeuralSystems/pycatch22
Project-URL: Mother Repository (catch22), https://github.com/DynamicsAndNeuralSystems/catch22
Classifier: Programming Language :: Python :: 3
Classifier: License :: OSI Approved :: GNU General Public License v3 or later (GPLv3+)
Classifier: Operating System :: OS Independent
License-File: LICENSE
